nerd/__init__.py
nerd/solver.py
nerd/calibration/__init__.py
nerd/calibration/best_density_function.py
nerd/calibration/fit_flow_rate.py
nerd/calibration/get_swath_width.py
nerd/calibration/model.py
nerd/calibration/rmse.py
nerd/density_functions/__init__.py
nerd/density_functions/density_functions.py
nerd/io/Nerd.py
nerd/io/__init__.py
nerd/io/geo2utm.py
nerd/io/import_data.py
nerd/mapping/__init__.py
nerd/mapping/tiling.py
geci_nerd-1.0.0.dist-info/licenses/LICENSE
geci_nerd-1.0.0.dist-info/WHEEL
geci_nerd-1.0.0.dist-info/METADATA
geci_nerd-1.0.0.dist-info/RECORD
