Metadata-Version: 2.4
Name: geci-nerd
Version: 1.0.0
Summary: The NERD algorithm performs calculations with increased accuracy, displaying results almost in real-time.
Author-email: Ciencia de Datos • GECI <ciencia.datos@islas.org.mx>
Requires-Python: >=3.8
Classifier: License :: OSI Approved :: GNU General Public License v3 or later (GPLv3+)
License-File: LICENSE
Requires-Dist: descartes
Requires-Dist: fiona
Requires-Dist: geojsoncontour
Requires-Dist: matplotlib==3.9.*
Requires-Dist: numpy
Requires-Dist: pandas
Requires-Dist: scipy
Requires-Dist: shapely
Requires-Dist: tqdm
Requires-Dist: utm
Project-URL: Source, https://github.com/IslasGECI/nerd
